setup.cfg
setup.py
libdrafter/__init__.py
libdrafter/parser.py
libdrafter_py.egg-info/PKG-INFO
libdrafter_py.egg-info/SOURCES.txt
libdrafter_py.egg-info/dependency_links.txt
libdrafter_py.egg-info/not-zip-safe
libdrafter_py.egg-info/requires.txt
libdrafter_py.egg-info/top_level.txt