Metadata-Version: 1.0
Name: libdrafter-py
Version: 0.1
Summary: Drafter binding for python.
Home-page: https://github.com/realityone/libdrafter-py
Author: UNKNOWN
Author-email: UNKNOWN
License: UNKNOWN
Platform: UNKNOWN
